smart_data_profiler/__init__.py
smart_data_profiler/profiler.py
smart_data_profiler/templates/report_template.html
smart_data_profiler-0.1.1.dist-info/licenses/LICENSE
smart_data_profiler-0.1.1.dist-info/METADATA
smart_data_profiler-0.1.1.dist-info/WHEEL
smart_data_profiler-0.1.1.dist-info/top_level.txt
smart_data_profiler-0.1.1.dist-info/RECORD
